mergeron/__init__.py
mergeron/_serialization.py
mergeron/core/__init__.py
mergeron/core/_process_ftc_merger_investigations_data.py
mergeron/core/empirical_margin_distribution.py
mergeron/core/ftc_merger_investigations_data.py
mergeron/core/guidelines_boundaries.py
mergeron/core/guidelines_boundary_functions.py
mergeron/core/pseudorandom_numbers.py
mergeron/data/__init__.py
mergeron/data/damodaran_margin_data_serialized.zip
mergeron/data/ftc_merger_investigations_data.zip
mergeron/gen/__init__.py
mergeron/gen/data_generation.py
mergeron/gen/data_generation_functions.py
mergeron/gen/enforcement_stats.py
mergeron/gen/upp_tests.py
mergeron/perks/__init__.py
mergeron/perks/guidelines_boundary_functions_extra.py
mergeron/py.typed
mergeron-2026.739636.6.dist-info/METADATA
mergeron-2026.739636.6.dist-info/WHEEL
mergeron-2026.739636.6.dist-info/licenses/docs/source/license.rst
mergeron-2026.739636.6.dist-info/RECORD
