Metadata-Version: 2.4
Name: mergeron
Version: 2026.739636.6
Summary: Python for analyzing merger enforcement policy
License-Expression: MIT
License-File: docs/source/license.rst
Keywords: merger enforcement policy,merger guidelines,merger screening,enforcement presumptions,concentration standards,diversion ratio,upward pricing pressure,GUPPI
Author: Murthy Kambhampaty
Author-email: smk@capeconomics.com
Requires-Python: >=3.12,<4.0
Classifier: Development Status :: 3 - Alpha
Classifier: Environment :: Console
Classifier: Intended Audience :: End Users/Desktop
Classifier: Intended Audience :: Science/Research
Classifier: Operating System :: OS Independent
Classifier: Programming Language :: Python
Classifier: Programming Language :: Python :: Implementation :: CPython
Classifier: Programming Language :: Python :: 3.12
Classifier: Programming Language :: Python :: 3.13
Classifier: Programming Language :: Python :: 3.14
Requires-Dist: aenum (>=3.1.16)
Requires-Dist: attrs (>=25.3.0)
Requires-Dist: backports.zstd ; python_version < "3.14"
Requires-Dist: beautifulsoup4 (>=4.13.4)
Requires-Dist: certifi (>=2025.6.15)
Requires-Dist: h5py (>=3.14.0)
Requires-Dist: hdf5plugin (>=6.0.0,<7.0.0)
Requires-Dist: jinja2 (>=3.1.6)
Requires-Dist: joblib (>=1.5.1)
Requires-Dist: kdepy (>=1.1.12)
Requires-Dist: lxml (>=6.0.0)
Requires-Dist: matplotlib (>=3.10.3)
Requires-Dist: mpmath (>=1.3.0)
Requires-Dist: python-calamine (>=0.4.0)
Requires-Dist: ruamel-yaml (>=0.18.14)
Requires-Dist: scipy (>=1.16.0)
Requires-Dist: sympy (>=1.14.0)
Requires-Dist: types-beautifulsoup4 (>=4.12.0.20250516)
Requires-Dist: urllib3 (>=2.5.0)
Project-URL: Homepage, https://mergeron.capeconomics.com/
Project-URL: Repository, https://github.com/capeconomics/mergeron.git
